{"version":3,"kind":"Notebook","sha256":"3ba1b4d05416fdb703730c940202192174faafc64c58b0bcf77091a8735a8ca3","slug":"notebooks.workflow.post-course","location":"/notebooks/workflow/post_course.md","dependencies":[],"frontmatter":{"title":"Post-Course Material","kernelspec":{"name":"python3","display_name":"Python 3"},"jupytext":{"text_representation":{"extension":".md","format_name":"myst","format_version":"0.13","jupytext_version":"1.19.1"}},"content_includes_title":true,"authors":[{"nameParsed":{"literal":"Alfonso Ladino","given":"Alfonso","family":"Ladino"},"name":"Alfonso Ladino","orcid":"0000-0001-8081-7827","github":"aladinor","id":"contributors-myst-generated-uid-0"},{"nameParsed":{"literal":"Anna del Moral Méndez","given":"Anna","non_dropping_particle":"del","family":"Moral Méndez"},"name":"Anna del Moral Méndez","orcid":"0000-0002-5015-840X","github":"adelmoral2","id":"contributors-myst-generated-uid-1"},{"nameParsed":{"literal":"Brenda Javornik","given":"Brenda","family":"Javornik"},"name":"Brenda Javornik","orcid":"0009-0004-9266-9293","github":"leavesntwigs","id":"contributors-myst-generated-uid-2"},{"nameParsed":{"literal":"Daniel Michelson","given":"Daniel","family":"Michelson"},"name":"Daniel Michelson","orcid":"0000-0003-3222-9881","github":"DanielMichelson","id":"contributors-myst-generated-uid-3"},{"nameParsed":{"literal":"Jen DeHart","given":"Jen","family":"DeHart"},"name":"Jen DeHart","orcid":"0000-0001-8536-4927","github":"jcdehart","id":"contributors-myst-generated-uid-4"},{"nameParsed":{"literal":"Kai Mühlbauer","given":"Kai","family":"Mühlbauer"},"name":"Kai Mühlbauer","orcid":"0000-0001-6599-1034","github":"kmuehlbauer","id":"contributors-myst-generated-uid-5"},{"nameParsed":{"literal":"Maxwell Grover","given":"Maxwell","family":"Grover"},"name":"Maxwell Grover","orcid":"0000-0002-0370-8974","github":"mgrover1","id":"contributors-myst-generated-uid-6"},{"nameParsed":{"literal":"Mike Dixon","given":"Mike","family":"Dixon"},"name":"Mike Dixon","orcid":"0000-0002-9597-9113","github":"mike-dixon","id":"contributors-myst-generated-uid-7"},{"nameParsed":{"literal":"Robert Jackson","given":"Robert","family":"Jackson"},"name":"Robert Jackson","orcid":"0000-0003-2518-1234","github":"rcjackson","id":"contributors-myst-generated-uid-8"},{"nameParsed":{"literal":"Scott Collis","given":"Scott","family":"Collis"},"name":"Scott Collis","orcid":"0000-0002-2303-687X","github":"scollis","id":"contributors-myst-generated-uid-9"},{"nameParsed":{"literal":"Ting-Yu Cha","given":"Ting-Yu","family":"Cha"},"name":"Ting-Yu Cha","orcid":"0000-0002-6292-8483","github":"tingyucha","id":"contributors-myst-generated-uid-10"},{"nameParsed":{"literal":"Zachary Sherman","given":"Zachary","family":"Sherman"},"name":"Zachary Sherman","orcid":"0000-0002-6455-8324","github":"zssherman","id":"contributors-myst-generated-uid-11"}],"github":"https://github.com/openradar/erad2026","copyright":"2026","settings":{"output_matplotlib_strings":"remove"},"numbering":{"title":{"offset":2}},"thumbnail":"/erad2026/build/radar_datatree_logo-9f68bc73e67e63a4718d8681362f37e4.png","exports":[{"format":"md","filename":"post_course.md","url":"/erad2026/build/post_course-30e8c0f5358d91953c5880d8ae1ab3ef.md"}]},"mdast":{"type":"root","children":[{"type":"block","children":[{"type":"grid","columns":[5],"children":[{"type":"grid-item","children":[{"type":"image","url":"/erad2026/build/radar_datatree_logo-9f68bc73e67e63a4718d8681362f37e4.png","alt":"radar datatree Logo","width":"150px","align":"center","key":"LpGCwzamlq","urlSource":"../../images/logos/radar_datatree_logo.png"}],"key":"Gcei2CS7pz"},{"type":"grid-item","children":[{"type":"image","url":"/erad2026/build/xradar_logo-e38427dbb50bb69ed66147ba2705ccaa.svg","alt":"xradar Logo","width":"150px","align":"center","key":"pOyX52Iwqn","urlSource":"../../images/logos/xradar_logo.svg"}],"key":"Zbak5GVqyl"},{"type":"grid-item","children":[{"type":"image","url":"/erad2026/build/Xarray_Icon_Final-b8c2a19192da6beb4fe80f589b1edecc.svg","alt":"xarray Logo","width":"150px","align":"center","key":"kK1uQAeoXQ","urlSource":"../../images/logos/Xarray_Icon_Final.svg"}],"key":"itGg1mNVI4"},{"type":"grid-item","children":[{"type":"image","url":"/erad2026/build/pyproj_logo-90b6e710fc7d27556949cce5faea85f0.svg","alt":"pyproj Logo","width":"150px","align":"center","key":"By9osOlXbx","urlSource":"../../images/logos/pyproj_logo.svg"}],"key":"m4aMPZJ1X7"},{"type":"grid-item","children":[{"type":"image","url":"/erad2026/build/wradlib_logo.svg-2f797fb9403a7cc98ece623542e036f2.png","alt":"wradlib Logo","width":"125px","align":"center","key":"zosoZdKAwV","urlSource":"../../images/logos/wradlib_logo.svg.png"}],"key":"JZ4KPGDCEP"}],"key":"LuCjSvNktX"},{"type":"heading","depth":1,"position":{"start":{"line":54,"column":1},"end":{"line":54,"column":1}},"children":[{"type":"text","value":"Post-Course Material","position":{"start":{"line":54,"column":1},"end":{"line":54,"column":1}},"key":"K8VB9zvPN4"}],"label":"workflow-post-course","identifier":"workflow-post-course","html_id":"workflow-post-course","key":"Nv439baCWp"},{"type":"paragraph","position":{"start":{"line":56,"column":1},"end":{"line":56,"column":1}},"children":[{"type":"text","value":"This section provides additional resources, references, and suggestions for further exploration beyond the main course exercises. Rather than introducing new mandatory material, it serves as a collection of pointers and comments intended to support continued learning and experimentation.","position":{"start":{"line":56,"column":1},"end":{"line":56,"column":1}},"key":"p39lMQucOO"}],"key":"IzYJw5FSzu"},{"type":"paragraph","position":{"start":{"line":58,"column":1},"end":{"line":58,"column":1}},"children":[{"type":"text","value":"Participants are encouraged to revisit the course datasets, explore alternative processing approaches, and consult the referenced documentation and literature for further study of radar data processing and evaluation techniques.","position":{"start":{"line":58,"column":1},"end":{"line":58,"column":1}},"key":"gU3LS79mwg"}],"key":"ggeI8jIUw3"},{"type":"paragraph","position":{"start":{"line":60,"column":1},"end":{"line":60,"column":1}},"children":[{"type":"text","value":"This section will be filled with content on the way to ERAD 2026. Check back regularly!","position":{"start":{"line":60,"column":1},"end":{"line":60,"column":1}},"key":"Pw03s9uANX"}],"key":"qYf6dTYW4k"}],"key":"FJKlcsu1Mn"}],"key":"UP94Fkrs5N"},"references":{"cite":{"order":[],"data":{}}},"footer":{"navigation":{"prev":{"title":"Clear Air Case 2026","url":"/notebooks/workflow/clear-air-case-2026","group":"Main Course"}}},"domain":"http://localhost:3000"}